hydropump/__init__.py
hydropump/backend.py
hydropump/instruction.py
hydropump/service.py
hydropump/test/TESTING.md
hydropump/test/__init__.py
hydropump/test/conftest.py
hydropump/test/unit/__init__.py
hydropump/test/unit/test_instructions.py
hydropump/test/unit/test_root/base/.gitignore
hydropump/test/unit/test_root/template/.gitignore
hydropump-0.1.4.dist-info/LICENSE
hydropump-0.1.4.dist-info/METADATA
hydropump-0.1.4.dist-info/WHEEL
hydropump-0.1.4.dist-info/RECORD
