Metadata-Version: 2.1
Name: hydropump
Version: 0.1.4
Summary: Configuration Management Library
License: MIT
Author: Michael Vecchione
Author-email: 51305946+mvecchione145@users.noreply.github.com
Requires-Python: >=3.10,<4.0
Classifier: License :: OSI Approved :: MIT License
Classifier: Programming Language :: Python :: 3
Classifier: Programming Language :: Python :: 3.10
Classifier: Programming Language :: Python :: 3.11
Requires-Dist: pyyaml (>=6.0,<7.0)
